counter_properties_pkg/__init__.py
counter_properties_pkg/counter_properties.py
example_pkg_offer_counter-0.0.3.dist-info/LICENSE
example_pkg_offer_counter-0.0.3.dist-info/METADATA
example_pkg_offer_counter-0.0.3.dist-info/WHEEL
example_pkg_offer_counter-0.0.3.dist-info/top_level.txt
example_pkg_offer_counter-0.0.3.dist-info/RECORD
