Metadata-Version: 2.1
Name: example-pkg-offer-counter
Version: 0.0.3
Summary: A Offer Counter
Home-page: https://github.com/pypa/sampleproject
Author: Sanket Dhumal
Author-email: sanketdhumal83@gmail.com
License: UNKNOWN
Platform: UNKNOWN
Classifier: Programming Language :: Python :: 3
Classifier: License :: OSI Approved :: MIT License
Classifier: Operating System :: OS Independent
Requires-Python: >=3.6
License-File: LICENSE
